kpn_theme/404.html
kpn_theme/__init__.py
kpn_theme/base.html
kpn_theme/main.html
kpn_theme/mkdocs_theme.yml
kpn_theme/nav.html
kpn_theme/search.html
kpn_theme/css/atom-dark-one.min.css
kpn_theme/css/bundle.css
kpn_theme/css/colors.css
kpn_theme/css/ir-black.min.css
kpn_theme/css/theme.css
kpn_theme/css/fonts/kpn-metric-bold.eot
kpn_theme/css/fonts/kpn-metric-bold.svg
kpn_theme/css/fonts/kpn-metric-bold.ttf
kpn_theme/css/fonts/kpn-metric-bold.woff
kpn_theme/css/fonts/kpn-metric-light.eot
kpn_theme/css/fonts/kpn-metric-light.svg
kpn_theme/css/fonts/kpn-metric-light.ttf
kpn_theme/css/fonts/kpn-metric-light.woff
kpn_theme/css/fonts/kpn-metric-normal.eot
kpn_theme/css/fonts/kpn-metric-normal.svg
kpn_theme/css/fonts/kpn-metric-normal.ttf
kpn_theme/css/fonts/kpn-metric-normal.woff
kpn_theme/css/fonts/kpn-metric-semi-bold.eot
kpn_theme/css/fonts/kpn-metric-semi-bold.svg
kpn_theme/css/fonts/kpn-metric-semi-bold.ttf
kpn_theme/css/fonts/kpn-metric-semi-bold.woff
kpn_theme/css/fonts/kpn-service-icons.eot
kpn_theme/css/fonts/kpn-service-icons.svg
kpn_theme/css/fonts/kpn-service-icons.ttf
kpn_theme/css/fonts/kpn-service-icons.woff
kpn_theme/css/fonts/kpn-ui-icons.eot
kpn_theme/css/fonts/kpn-ui-icons.svg
kpn_theme/css/fonts/kpn-ui-icons.ttf
kpn_theme/css/fonts/kpn-ui-icons.woff
kpn_theme/fonts/kpn-metric-bold.eot
kpn_theme/fonts/kpn-metric-bold.svg
kpn_theme/fonts/kpn-metric-bold.ttf
kpn_theme/fonts/kpn-metric-bold.woff
kpn_theme/fonts/kpn-metric-light.eot
kpn_theme/fonts/kpn-metric-light.svg
kpn_theme/fonts/kpn-metric-light.ttf
kpn_theme/fonts/kpn-metric-light.woff
kpn_theme/fonts/kpn-metric-normal.eot
kpn_theme/fonts/kpn-metric-normal.svg
kpn_theme/fonts/kpn-metric-normal.ttf
kpn_theme/fonts/kpn-metric-normal.woff
kpn_theme/fonts/kpn-metric-semi-bold.eot
kpn_theme/fonts/kpn-metric-semi-bold.svg
kpn_theme/fonts/kpn-metric-semi-bold.ttf
kpn_theme/fonts/kpn-metric-semi-bold.woff
kpn_theme/fonts/kpn-service-icons.eot
kpn_theme/fonts/kpn-service-icons.svg
mkdocs_kpn-1.7.3.dist-info/LICENSE
mkdocs_kpn-1.7.3.dist-info/METADATA
mkdocs_kpn-1.7.3.dist-info/WHEEL
mkdocs_kpn-1.7.3.dist-info/entry_points.txt
mkdocs_kpn-1.7.3.dist-info/top_level.txt
mkdocs_kpn-1.7.3.dist-info/RECORD
