Metadata-Version: 2.1
Name: mkdocs-kpn
Version: 1.7.3
Summary: A KPN-styles theme for MkDocs
Home-page: https://github.com/kpn/mkdocs-kpn-theme
Author: Santiago Fraire Willemoës
Author-email: de-ddci@kpn.com
License: MIT
Keywords: mkdocs,documentation,theme
Classifier: Development Status :: 5 - Production/Stable
Classifier: License :: OSI Approved :: MIT License
Classifier: Programming Language :: JavaScript
Classifier: Programming Language :: Python
Classifier: Topic :: Documentation
Classifier: Topic :: Text Processing :: Markup :: HTML
License-File: LICENSE
Requires-Dist: mkdocs >=1.0
Requires-Dist: markdown >=3.3.7
Requires-Dist: pymdown-extensions >=9.4
Requires-Dist: plantuml-markdown <4,>=3.4.2
